graphs_wendyhielo/__init__.py
graphs_wendyhielo/heapq.py
graphs_wendyhielo/sp.py
graphs_wendyhielo-0.1.0.dist-info/METADATA
graphs_wendyhielo-0.1.0.dist-info/WHEEL
graphs_wendyhielo-0.1.0.dist-info/top_level.txt
graphs_wendyhielo-0.1.0.dist-info/RECORD
