Metadata-Version: 2.4
Name: graphs_wendyhielo
Version: 0.1.0
Summary: Graph algorithms package featuring Dijkstra's shortest path
Author: wendyhielo
Requires-Python: >=3.8
